setup.py
client/__init__.py
client/api.py
client/config.py
client/exception.py
client/main.py
client/register.py
shenyu_client.egg-info/PKG-INFO
shenyu_client.egg-info/SOURCES.txt
shenyu_client.egg-info/dependency_links.txt
shenyu_client.egg-info/entry_points.txt
shenyu_client.egg-info/requires.txt
shenyu_client.egg-info/top_level.txt